contextfree/__init__.py
contextfree/_transform.py
contextfree/_version.py
contextfree/color.py
contextfree/core.py
contextfree/random.py
contextfree/rule.py
contextfree/shapes.py
contextfree-0.3.7.dist-info/LICENSE
contextfree-0.3.7.dist-info/METADATA
contextfree-0.3.7.dist-info/WHEEL
contextfree-0.3.7.dist-info/top_level.txt
contextfree-0.3.7.dist-info/RECORD
