Metadata-Version: 2.1
Name: contextfree
Version: 0.3.7
Summary: cfdg-inspired cairo-based pythonic generative art framework
Home-page: https://github.com/undertherain/pycontextfree
Download-URL: 
Author: 
Author-email: 
Maintainer: 
Maintainer-email: 
License: Apache License 2.0
Keywords: generative,art,graphics
Classifier: Development Status :: 3 - Alpha
Classifier: Environment :: Console
Classifier: License :: OSI Approved :: Apache Software License
Classifier: Natural Language :: English
Classifier: Operating System :: POSIX
Classifier: Programming Language :: Python :: 3.5
Classifier: Programming Language :: Python :: 3.6
Classifier: Programming Language :: Python :: 3 :: Only
Requires-Python: >=3.5
License-File: LICENSE
Requires-Dist: cairocffi
Requires-Dist: numpy
